Ejercicio1_Mikexy21/__init__.py
Ejercicio1_Mikexy21/cursos.py
Ejercicio1_Mikexy21/utils.py
Ejercicio1_Mikexy21-0.1.0.dist-info/METADATA
Ejercicio1_Mikexy21-0.1.0.dist-info/WHEEL
Ejercicio1_Mikexy21-0.1.0.dist-info/top_level.txt
Ejercicio1_Mikexy21-0.1.0.dist-info/RECORD
