Metadata-Version: 2.1
Name: Ejercicio1_Mikexy21
Version: 0.1.0
Summary: Ejemplo 1
Author: Mikeee
